croad/__init__.py
croad/__main__.py
croad/croad.py
croad/interact.py
croad/plt.py
croad/spline.py
croad/utils.py
croad-0.1.1.dist-info/METADATA
croad-0.1.1.dist-info/WHEEL
croad-0.1.1.dist-info/entry_points.txt
croad-0.1.1.dist-info/RECORD
