Metadata-Version: 2.3
Name: croad
Version: 0.1.1
Summary: Add your description here
Author-email: todo <todo@todo.todo>
Requires-Python: >=3.10
Requires-Dist: autonomous-proto>=0.1.4
Requires-Dist: geomdl>=5.4.0
Requires-Dist: matplotlib>=3.10.3
Requires-Dist: numpy>=2.2.6
Requires-Dist: pydantic>=2.11.7
Requires-Dist: pymap3d>=3.2.0
Requires-Dist: pyside6>=6.9.1
Requires-Dist: questionary[fuzzy]>=2.1.0
Requires-Dist: rosbags>=0.10.10
Requires-Dist: scipy>=1.15.3
Requires-Dist: typer>=0.16.0
